{
  "turn_count": 22,
  "cards_played": {
    "Copper": 93,
    "Patrician": 51,
    "Forager": 47,
    "Emporium": 10,
    "Silver": 5,
    "Skulk": 5,
    "Gold": 3
  },
  "victory_points": {
    "GeneticAI-140428808255008": 20,
    "GeneticAI-140428808237616": 20
  },
  "actions_played": {
    "GeneticAI-140428808255008": 49,
    "GeneticAI-140428808237616": 64
  },
  "cards_bought": {
    "Patrician": 10,
    "Forager": 10,
    "Copper": 21,
    "Emporium": 10,
    "Silver": 7,
    "Skulk": 2,
    "Province": 5
  }
}
